<teiHeader>
<fileDesc>
<titleStmt>
  <title>แสดงศิลปะ  </title>
  <author>เอพี  </author>
</titleStmt>
<publicationStmt>
  <publisher>มติชน  </publisher>
  <pubPlace>http://www.matichon.co.th/  </pubPlace>
  <date>2009-06-07 00:00:00  </date>
</publicationStmt>
<notesStmt>
  <note>ต่างประเทศ  </note>
</notesStmt>
<sourceDesc>
  <bibl>http://www.matichon.co.th/matichon/view_news.php?newsid=01for05070652&sectionid=0104&day=2009-06-07  </bibl>
</sourceDesc>
</fileDesc>
</teiHeader>
<news>
<headline>แสดงศิลปะ</headline>
<lead></lead>
<neck></neck>
<body><p><persName>มิเชบังเกโร พิสโตเลตโต</persName> ศิลปินชาวอิตาลี กำลังแสดงงานศิลปะด้วยการทุบกระจกเพื่อสร้างงานชิ้นเอกที่เรียกว่า "Twentytwo less two" ในวันที่ 2 ของงานแสดงศิลปะระหว่างประเทศบินเนลครั้งที่ 53 ที่เมืองเวนิซ ประเทศอิตาลี เมื่อวันที่ 5 มิถุนายน</p></body>
</news>
