<teiHeader>
<fileDesc>
<titleStmt>
  <title>"แป้ง"โชว์เซ็กซี่ยืนยันไม่ใช่คนเจ้าชู้  </title>
  <author>แนวหน้า  </author>
</titleStmt>
<publicationStmt>
  <publisher>แนวหน้า  </publisher>
  <pubPlace>http://www.naewna.com  </pubPlace>
  <date>2009-07-06 00:00:00  </date>
</publicationStmt>
<notesStmt>
  <note>บันเทิง  </note>
</notesStmt>
<sourceDesc>
  <bibl>http://www.naewna.com/news.asp?ID=168935  </bibl>
</sourceDesc>
</fileDesc>
</teiHeader>
<news>
<headline>"แป้ง"โชว์เซ็กซี่ยืนยันไม่ใช่คนเจ้าชู้</headline>
<lead></lead>
<neck></neck>
<body><p>ไม่แปลกถ้า "แป้ง-อรจิรา แหลมวิไล" จะติดโผ FHM 100 SEXIEST WOMEN THE WORLD 2009 ของ<orgName>นิตยสาร FHM</orgName> เพราะความสวยและเซ็กซี่ของเธอไม่เป็นรองใคร ล่าสุดกระชากใจหนุ่มๆ บนปก<orgName>นิตยสาร FHM</orgName> เดือนกรกฎาคม โดยเจ้าตัวเผยว่า </p>

 <p>"แป้งไม่ใช่คนเจ้าชู้ แป้งไม่ใช่คาสซาโนวี่ค่ะ ไม่ขนาดนั้น แป้งคบทีละคน ส่วนคนเจ้าชู้คือมีคนที่เรารักมาแล้วก็ยังไม่พอ แต่แป้งยังไม่มีใครที่ใช่ ก็จะดูไปเรื่อยๆ แต่ถ้าวันนึงแป้งรักใครซักคนก็จะไม่เจ้าชู้ค่ะ มีแค่คนเดียว แป้งไม่เคยจีบผู้ชายก่อน รู้สึกไม่กล้า เขาต้องเข้ามาเองสิ ถ้าเราเข้าไปเองมันจะรู้สึกว่าไม่มีฟอร์ม ไม่รู้สิ ส่วนเวลาผู้ชายมาจีบให้เข้ามาเป็นเพื่อนนะคะ อย่ามาเลี่ยนๆหวานๆ มากก็ไม่ชอบ" แป้งกล่าว</p></body>
</news>
