<teiHeader>
<fileDesc>
<titleStmt>
  <title>พรรคภูมิใจไทย จัดระดมสมาชิกพรรคและสื่อมวลชนร่วมบริจาคโลหิตถวายเป็นพระราชกุศลแด่สมเด็จพระนางเจ้า ฯ พระบรมราชินีนาถ  </title>
  <author>กัลยา คงยั่งยืน  </author>
</titleStmt>
<publicationStmt>
  <publisher>สำนักข่าวแห่งชาติ กรมประชาสัมพันธ์  </publisher>
  <pubPlace>http://thainews.prd.go.th  </pubPlace>
  <date>2009-08-11 00:00:00  </date>
</publicationStmt>
<notesStmt>
  <note>การเมือง  </note>
</notesStmt>
<sourceDesc>
  <bibl>http://thainews.prd.go.th/view.php?m_newsid=255208110207&tb=N255208&return=ok&news_headline  </bibl>
</sourceDesc>
</fileDesc>
</teiHeader>
<news>
<headline>พรรคภูมิใจไทย จัดระดมสมาชิกพรรคและสื่อมวลชนร่วมบริจาคโลหิตถวายเป็นพระราชกุศลแด่สมเด็จพระนางเจ้า ฯ พระบรมราชินีนาถ</headline>
<lead></lead>
<neck></neck>
<body><p>พรรคภูมิใจไทย จัดระดมสมาชิกพรรคและสื่อมวลชนร่วมบริจาคโลหิตถวายเป็นพระราชกุศลแด่สมเด็จพระนางเจ้า ฯ พระบรมราชินีนาถ เนื่องในวันแม่ 12 สิงหาคม บรรดาแกนนำของพรรคภูมิใจไทย ร่วมกิจกรรมระดมสมาชิกพรรคและสื่อมวลชนร่วมบริจาคโลหิตถวายเป็นพระกุศลแด่สมเด็จพระนางเจ้าพระบรมราชินีนารถเนื่องในวันแม่ 12 สิงหาคม เช่น<persName>นายบุญจง วงศ์ไตรรัตน์</persName> รัฐมนตรีช่วยว่าการกระทรวงมหาดไทย <persName>นายมานิต นพอมรบดี</persName> รัฐมนตรีช่วยว่าการกระทรวงสาธารณะสุข <persName>นายศุภชัย โพธิ์สุ</persName> รัฐมนตรีช่วยว่าการกระทรวงเกษตรและสหกรณ์ <persName>นายโสภณ ซารัมย์</persName> รัฐมนตรีว่าการกระทรวงคมนาคม และ<persName>นายสมศักดิ์ เทพสุทิน</persName> แกนนำพรรค ได้ร่วมบริจาคด้วย เพื่อถวายเป็นพระราชกุศลแด่สมเด็จพระนางเจ้า ฯ พระบรมราชินีนาถ เนื่องในวันแม่แห่งชาติ 12 สิงหาคม โดย มีศิลปินดารานักแสดงจากหลายสังกัดมาให้กำลังใจและร่วมบริจาคโลหิตด้วยเช่นกัน อย่างไรก็ตามกิจกรรมนี้ทั้ง<persName>นายชวรัตน์ ชาญวีรกูล</persName> และ<persName>นางพรทิวา นาคาศัย</persName> ไม่ได้ร่วมบริจาคด้วย โดย<persName>นายชวรัตน์</persName> มีอายุเกินเกณฑ์ที่กำหนดไว้ ขณะที่<persName>นางพรทิวา</persName>ก็ไม่ได้ร่วมบริจาคเช่นกันเนื่องจากพักผ่อนไม่เพียงพอ </p></body>
</news>
