<teiHeader>
<fileDesc>
<titleStmt>
  <title>สภาเริ่มประชุมกรอบข้อตกลงชายแดนไทย-เขมร  </title>
  <author>ไอ.เอ็น.เอ็น  </author>
</titleStmt>
<publicationStmt>
  <publisher>ไอ.เอ็น.เอ็น  </publisher>
  <pubPlace>http://www.innnews.co.th/  </pubPlace>
  <date>2009-08-31 12:19:45  </date>
</publicationStmt>
<notesStmt>
  <note>การเมือง  </note>
</notesStmt>
<sourceDesc>
  <bibl>http://www.innnews.co.th/politic.php?nid=187648  </bibl>
</sourceDesc>
</fileDesc>
</teiHeader>
<news>
<headline>สภาเริ่มประชุมกรอบข้อตกลงชายแดนไทย-เขมร</headline>
<lead>ที่ประชุมสภา เริ่มพิจารณาเรื่องกรอบข้อตกลงชายแดน ไทย-กัมพูชา แล้ว หลังถกเถียงนาน 30 นาท</lead>
<neck></neck>
<body><p>การประชุมร่วมรัฐสภา เพื่อพิจารณาร่างกรอบการเจรจา เพื่อรักษาความมั่นคงและความเรียบร้อย บริเวณพื้นที่ชายแดนไทยกัมพูชา ในกรอของคณะกรรมาธิการชายแดนทั่วไปไทย-กัมพูชา และคนไทยอื่น ๆ รวมทั้ง บันทึกความเข้าใจกับนานาประเทศ อาทิ อินเดีย ฟิลิปปินส์ ยูเครน ได้เริ่มต้นขึ้นแล้ว หลังจากที่ประชุมรัฐสภา ได้มีการถกเถียงกันนานกว่าครึ่ง ช.ม. เรื่องการเลื่อนวาระดังกล่าวขึ้นมาพิจารณา และท้ายที่สุด ที่ประชุมได้มีมติเสียงข้างมาก ให้เลื่อนวาระดังกล่าวขึ้นมาพิจารณาก่อน </p>
<p>โดย <persName>พล.อ.ประวิตร วงษ์สุวรรณ</persName> รัฐมนตรีว่าการกระทรวงกลาโหม ได้เสนอให้ที่ประชุมมีการประชุมลับเนื่องจากเห็นว่า เรื่องดังกล่าวเป็นเรื่องละเอียดอ่อน ที่เกี่ยวข้องกับประเทศเพื่อนบ้าน ดังนั้น หากมีการถ่ายทอดสด อาจจะกระทบกับความสัมพันธ์ที่ดีระหว่างประเทศได้ </p></body>
</news>
