<teiHeader>
<fileDesc>
<titleStmt>
  <title>กองทัพฟิลิปปินส์ระบุว่า กลุ่มกบฏมุสลิมเกือบ 100 คน ถูกสังหารในช่วง 2 สัปดาห์ที่ผ่านมา  </title>
  <author>พรทิพย์ แสงมหาชัย  </author>
</titleStmt>
<publicationStmt>
  <publisher>สำนักข่าวแห่งชาติ กรมประชาสัมพันธ์  </publisher>
  <pubPlace>http://thainews.prd.go.th  </pubPlace>
  <date>2009-06-16 00:00:00  </date>
</publicationStmt>
<notesStmt>
  <note>ต่างประเทศ  </note>
</notesStmt>
<sourceDesc>
  <bibl>http://thainews.prd.go.th/view.php?m_newsid=255206150290&tb=N255206&return=ok&news_headline="%a1%cd%a7%b7%d1%be%bf%d4%c5%d4%bb%bb%d4%b9%ca%ec%c3%d0%ba%d8%c7%e8%d2%20%a1%c5%d8%e8%c1%a1%ba%af%c1%d8%ca%c5%d4%c1%e0%a1%d7%cd%ba%20100%20%a4%b9%20%b6%d9%a1%ca%d1%a7%cb%d2%c3%e3%b9%aa%e8%c7%a7%202%20%ca%d1%bb%b4%d2%cb%ec%b7%d5%e8%bc%e8%d2%b9%c1%d2"  </bibl>
</sourceDesc>
</fileDesc>
</teiHeader>
<news>
<headline>กองทัพ<placeName>ฟิลิปปินส์</placeName>ระบุว่า กลุ่มกบฏมุสลิมเกือบ 100 คน ถูกสังหารในช่วง 2 สัปดาห์ที่ผ่านมา</headline>
<lead></lead>
<neck></neck>
<body><p>กองกำลังทหาร<placeName>ฟิลิปปินส์</placeName>กล่าววันนี้ว่า กลุ่มกบฏมุสลิมแบ่งแยกดินแดนเกือบร้อยคนถูกสังหารในช่วง 2 สัปดาห์ที่ผ่านมาจากเหตุสู้รบรุนแรงทางใต้ของ<placeName>ฟิลิปปินส์</placeName> พันเอกเมดาร์โด เกซลานี ผู้บัญชาการกองกำลังทหารประจำภูมิภาคกล่าวว่า เจ้าหน้าที่พบผู้เสียชีวิตราว 54 – 56 คน ขณะที่ร่างของผู้เสียชีวิตรายอื่น ชาวบ้านได้ขนย้ายออกไปจากพื้นที่ทำให้ตัวเลขของผู้เสียชีวิตทั้งหมดขณะนี้อยู่ที่ 96 ราย ทั้งนี้เหตุสู้รบระหว่างกองกำลังทหารกับกลุ่มกบฎโมโร เริ่มขึ้นเมื่อวันที่ 4 มิถุนายนที่ผ่านมาในจังหวัดทางใต้ของ<placeName>เกาะมินดาเนา</placeName> โดยกลุ่มกบฎโมโร เริ่มต่อสู้แบ่งแยกดินแดนตั้งแต่ปี 2521.</p></body>
</news>
