<teiHeader>
<fileDesc>
<titleStmt>
  <title>ร้องรัฐเร่งแก้ปัญหาเขาพระวิหาร  </title>
  <author>เดลินิวส์  </author>
</titleStmt>
<publicationStmt>
  <publisher>เดลินิวส์  </publisher>
  <pubPlace>http://www.dailynews.co.th  </pubPlace>
  <date>2009-09-28 13:05:00  </date>
</publicationStmt>
<notesStmt>
  <note>การเมือง  </note>
</notesStmt>
<sourceDesc>
  <bibl>http://dailynews.co.th/newstartpage/index.cfm?page=content&categoryID=8&contentID=22982  </bibl>
</sourceDesc>
</fileDesc>
</teiHeader>
<news>
<headline>ร้องรัฐเร่งแก้ปัญหาเขาพระวิหาร</headline>
<lead></lead>
<neck></neck>
<body><p>วันนี้ (28 ก.ย.) ที่รัฐสภา ผู้สื่อข่าวรายงานว่า ในการประชุมวุฒิสภา <persName>นายสิงห์ชัย ทุ่งทอง</persName> สมาชิกวุฒิสภาจังหวัดอุทัยธานี ได้หารือต่อที่ประชุมถึงกรณีเหตุการณ์ที่มีคนไทย 2 กลุ่มไล่ทำร้ายกัน เนื่องจากมีความคิดขัดแย้งกันเรื่องปราสาทเขาพระวิหาร จนเป็นเรื่องใหญ่ทำให้คนไทยแตกแยกกัน แต่เท่าที่ผ่านมา 1 ปี รัฐบาลก็นิ่งเฉย ในวุฒิสภาก็ไม่มีใครรู้เรื่องจริง รัฐบาลปล่อยปละละเลย จึงต้องการให้รัฐอธิบายให้ความรู้กับประชาชนให้เข้าใจชัดเจนว่า ปัญหาคืออะไร และบอกถึงแนวทางการแก้ไข มิเช่นนั้นเรื่องนี้ก็จะถูกนำไปเป็นเครื่องมือทางการเมืองอยู่ตลอดเวลา.
</p></body>
</news>
