<teiHeader>
<fileDesc>
<titleStmt>
  <title>มือมืดควบ จยย.สุ่มยิงปืนใส่"ช่างกลปทุมวัน" นศ.เจ็บ 3 ราย  </title>
  <author>มติชนออนไลน์  </author>
</titleStmt>
<publicationStmt>
  <publisher>มติชน  </publisher>
  <pubPlace>http://www.matichon.co.th/  </pubPlace>
  <date>2010-01-12 13:08:19  </date>
</publicationStmt>
<notesStmt>
  <note>อาชญากรรม  </note>
</notesStmt>
<sourceDesc>
  <bibl>http://www.matichon.co.th/news_detail.php?newsid=1263276512&catid=17  </bibl>
</sourceDesc>
</fileDesc>
</teiHeader>
<news>
<headline>มือมืดควบ จยย.สุ่มยิงปืนใส่"ช่างกลปทุมวัน" นศ.เจ็บ 3 ราย</headline>
<lead></lead>
<neck></neck>
<body><p>ผู้สื่อข่าวรายงานว่า เกิดเหตุคนร้าย 2 คนขับจักรยานยนต์มาหน้าสถาบันเทคโนโลยีปทุมวัน ถ.พระราม 1 ก่อนชักปืนยิงใส่นักศึกษา ที่ยืนอยู่ใกล้เคียง ส่งผลให้มีนักศึกษาช่างกลปทุมวันบาดเจ็บ 3 คน เจ้าหน้าที่ของสถาบันฯ นำส่งโรงพยาบาลหัวเฉียว 2 คน เบื้องต้นทราบชื่อ 1 คน คือ<persName>นายอัครพงษ์</persName> ยังไม่ทราบนามสกุล ถูกกระสุนเข้าที่ขา อีกคนอาการสาหัสถูกกระสุน 2 นัด ส่วนผู้บาดเจ็บอีกคนนำส่งโรงพยาบาลจุฬาลงกรณ์ สำหรับสาเหตุอยู่ระหว่างการสอบสวนของเจ้าหน้าที่ตำรวจ </p></body>
</news>
