<teiHeader>
<fileDesc>
<titleStmt>
  <title>บช.น.ประชุมหาแนวทางติดตามคนร้ายป่วนบึ้ม  </title>
  <author>ทีมข่าวอาชญากรรม  </author>
</titleStmt>
<publicationStmt>
  <publisher>ผู้จัดการออนไลน์  </publisher>
  <pubPlace>http://www.manager.co.th  </pubPlace>
  <date>2010-03-28 21:17:00  </date>
</publicationStmt>
<notesStmt>
  <note>อาชญากรรม  </note>
</notesStmt>
<sourceDesc>
  <bibl>http://www.manager.co.th/Crime/ViewNews.aspx?NewsID=9530000043195  </bibl>
</sourceDesc>
</fileDesc>
</teiHeader>
<news>
<headline>บช.น.ประชุมหาแนวทางติดตามคนร้ายป่วนบึ้ม</headline>
<lead></lead>
<neck></neck>
<body><teiHeader>
<fileDesc>
<titleStmt>
  <title>บช.น.ประชุมหาแนวทางติดตามคนร้ายป่วนบึ้ม  </title>
  <author>ทีมข่าวอาชญากรรม  </author>
</titleStmt>
<publicationStmt>
  <publisher>ผู้จัดการออนไลน์  </publisher>
  <pubPlace>http://www.manager.co.th  </pubPlace>
  <date>2010-03-28 21:17:00  </date>
</publicationStmt>
<notesStmt>
  <note>อาชญากรรม  </note>
</notesStmt>
<sourceDesc>
  <bibl>http://www.manager.co.th/Crime/ViewNews.aspx?NewsID=9530000043195  </bibl>
</sourceDesc>
</fileDesc>
</teiHeader>
<news>
<headline>บช.น.ประชุมหาแนวทางติดตามคนร้ายป่วนบึ้ม</headline>
<lead></lead>
<neck></neck>
<body></body>
</news></body>
</news>
