<teiHeader>
<fileDesc>
<titleStmt>
  <title>ประธานวิปฝ่ายค้าน กล่าวถึงพรรคภูมิใจไทยเสนอ ร่างพ.ร.บ.นิรโทษกรรม ต้องมีการหารือหลายฝ่าย  </title>
  <author>คณิต จินดาวรรณ  </author>
</titleStmt>
<publicationStmt>
  <publisher>สำนักข่าวแห่งชาติ กรมประชาสัมพันธ์  </publisher>
  <pubPlace>http://thainews.prd.go.th  </pubPlace>
  <date>2009-08-20 00:00:00  </date>
</publicationStmt>
<notesStmt>
  <note>การเมือง  </note>
</notesStmt>
<sourceDesc>
  <bibl>http://thainews.prd.go.th/view.php?m_newsid=255208200117&tb=N255208&return=ok&news_headline  </bibl>
</sourceDesc>
</fileDesc>
</teiHeader>
<news>
<headline>ประธาน<orgName>วิปฝ่ายค้าน</orgName> กล่าวถึง<orgName>พรรคภูมิใจไทย</orgName>เสนอ ร่างพ.ร.บ.นิรโทษกรรม ต้องมีการหารือหลายฝ่าย</headline>
<lead></lead>
<neck></neck>
<body><p>ประธาน<orgName>วิปฝ่ายค้าน</orgName> ระบุ การเสนอร่าง พ.ร.บ.นิรโทษกรรมของ<orgName>พรรคภูมิใจไทย</orgName> ต้องมีการหารือหลายฝ่าย นายวิทยา บุรณศิริ ประธาน<orgName>วิปฝ่ายค้าน</orgName> กล่าวถึงกรณีที่ <orgName>พรรคภูมิใจไทย</orgName>เสนอ ร่างพ.ร.บ.นิรโทษกรรม เข้าสู่การพิจาณาของ<orgName>สภาผู้แทนราษฎร</orgName>ว่า ต้องดูที่รายละเอียด แต่ที่ฟังจากเหตุผลของนายชวรัตน์ ชาญวีรกูล รัฐมนตรีว่าการ<orgName>กระทรวงมหาดไทย</orgName>หัวหน้า<orgName>พรรคภูมิใจไทย</orgName> เป็นเจตนาที่ดีที่ต้องการลดความขัดแย้ง ซึ่งต้องมีการหารือหลายฝ่าย และเป็นแนวทางทางเดียวกับ<orgName>คณะกรรมการสมานฉันท์ฯ</orgName> ที่<orgName>สภาผู้แทนราษฎร</orgName>พิจารณาหรือไม่ หากเป็นไปในทิศทางเดียวกันอาจจะนำมาพิจารณาเพื่อให้เป็นประโยชน์ร่วมกัน ส่วนกรณีที่<orgName>สภาองค์กรวิทยุโทรทัศน์ท้องถิ่นแห่งประเทศไทย</orgName>ทำหนังสือร้องเรียนเรื่องคลื่นความถี่วิทยุกระจายเสียง ประธาน<orgName>วิปฝ่ายค้าน</orgName> กล่าวว่า เป็นเรื่องน่าเห็นใจ เพราะอยู่ในช่วงรอยต่อของกฎหมายและมีการประมูลคลื่นความถี่ที่ใช้ในกิจการวิทยุกระจายเสียง ซึ่งเกรงว่าจะไม่ได้รับความเป็นธรรมจึงเรียกร้องมายังฝ่ายค้าน เพื่อติดตามการปฏิบัติหน้าที่ของรัฐบาลต่อไป</p></body>
</news>
