<teiHeader>
<fileDesc>
<titleStmt>
  <title>ปล่อยกู้ซื้อรถตู้วิน  </title>
  <author>ข่าวสด  </author>
</titleStmt>
<publicationStmt>
  <publisher>ข่าวสด  </publisher>
  <pubPlace>http://www.khaosod.co.th  </pubPlace>
  <date>2009-05-15 00:00:00  </date>
</publicationStmt>
<notesStmt>
  <note>เศรษฐกิจ  </note>
</notesStmt>
<sourceDesc>
  <bibl>http://www.matichon.co.th/khaosod/view_news.php?newsid=TURObFkyOHhPVEUxTURVMU1nPT0=&sectionid=TURNd05RPT0=&day=TWpBd09TMHdOUzB4TlE9PQ==  </bibl>
</sourceDesc>
</fileDesc>
</teiHeader>
<news>
<headline>ปล่อยกู้ซื้อรถตู้วิน</headline>
<lead></lead>
<neck></neck>
<body><p>นายธีรศักดิ์ สุวรรณยศ กรรมการผู้จัดการ ธนาคารอิสลามแห่งประเทศไทย (ธอท.) เปิดเผยว่า ธอท.ร่วมลงนามกับบริษัทเมืองไทยประกันภัย บริษัทกมลประกันภัย บริษัทแพล็ททินัมมอเตอร์เซลล์ และสมาคมรถตู้โดยสารต่างจังหวัดแห่งประเทศไทย ในโครงการสินเชื่อเช่าซื้อรถยนต์เพื่อสร้างอาชีพใหม่ ให้กับผู้ประกอบการรถยนต์ตู้โดยสารสาธารณะจังหวัด 1,000 คน เงินสินเชื่อ 1,000 ล้านบาท ซึ่งขณะนี้มียอดจองเข้าแล้ว 200 คัน วงเงิน 200 ล้านบาท และมีแผนจะปล่อยสินเชื่อเช่าซื้อแท็กซี่และตุ๊กตุ๊กเพิ่มเติม</p></body>
</news>
