<teiHeader>
<fileDesc>
<titleStmt>
  <title>สาธิตแนะขายข้าว,มันสำปะหลังแบบรัฐต่อรัฐ  </title>
  <author>ไอ.เอ็น.เอ็น  </author>
</titleStmt>
<publicationStmt>
  <publisher>ไอ.เอ็น.เอ็น  </publisher>
  <pubPlace>http://www.innnews.co.th/  </pubPlace>
  <date>2009-05-17 13:35:14  </date>
</publicationStmt>
<notesStmt>
  <note>เศรษฐกิจ  </note>
</notesStmt>
<sourceDesc>
  <bibl>http://www.innnews.co.th/biz.php?nid=171698  </bibl>
</sourceDesc>
</fileDesc>
</teiHeader>
<news>
<headline>สาธิตแนะขาย<name>ข้าว</name>,<name head="มัน">มันสำปะหลัง</name>แบบ<name>รัฐต่อรัฐ</name></headline>
<lead>สาธิต ปิตุเตชะ <name>ส.ส.</name>ปชป.แนะ ก.พาณิชย์ เสนอการส่งออก<name>ข้าว</name>และ<name head="มัน">มันสำปะหลัง</name>แบบ<name>รัฐต่อรัฐ</name> เพื่อทำให้ราคาสูงและแก้ปัญหาทุจริต</lead>
<neck></neck>
<body><p>นายสาธิต ปิตุเตชะ <name head="ส.ส.">ส.ส.ระยอง</name> พรรคประชาธิปัตย์ ในฐานะ<name head="รองประธาน">รองประธานคณะกรรมาธิการการพาณิชย์สภาผู้แทนราษฎร</name> กล่าวถึงปัญหาการระบายสินค้าทางการเกษตร โดยเฉพาะ<name>ข้าวโพด</name> 4.4 แสนต้น ที่มีปัญหาผลประโยชน์และทำให้รัฐบาลขาดทุนว่า การส่งออก<name>ข้าว</name>และ<name>มัน</name>ที่กำลังจะมีขึ้นนั้นขอเรียกร้องให้ นางพรทิวา นาคาศัย <name head="รมว.">รมว.พาณิชย์</name> แนะรัฐบาลเสนอขาย<name>ข้าว</name>แบบ <name>G-to-G</name> หรือ <name>รัฐต่อรัฐ</name> เพื่อแก้ไขปัญหาการทุจริต รวมถึงสามารถขาย<name>ข้าว</name>ได้ในราคาตลาด เนื่องจากที่ผ่านมารัฐบาลขาย<name>ข้าว</name>ได้ต่ำกว่าราคาตลาด อีกทั้งวิธีการดังกล่าวจะทำให้ต่ำกว่าราคาจำนำ กว่า 4,000 บาท ซึ่งจะแก้ไขปัญหาการเอื้อประโยชน์ให้กลุ่มใดกลุ่มหนึ่งหรือการทุจริตได้
</p></body>
</news>
